amap/__init__.py
amap/amap.conf
amap/cli.py
amap/main.py
amap/config/__init__.py
amap/config/atlas.py
amap/download/__init__.py
amap/download/cli.py
amap/download/download.py
amap/register/__init__.py
amap/register/brain_processor.py
amap/register/brain_registration.py
amap/register/registration_params.py
amap/register/tools.py
amap/register/volume.py
amap/tools/__init__.py
amap/tools/image.py
amap/utils/__init__.py
amap/utils/run.py
amap/utils/transformations.py
amap/vis/__init__.py
amap/vis/boundaries.py
amap-0.1.26.dist-info/LICENSE
amap-0.1.26.dist-info/METADATA
amap-0.1.26.dist-info/WHEEL
amap-0.1.26.dist-info/entry_points.txt
amap-0.1.26.dist-info/top_level.txt
amap-0.1.26.dist-info/RECORD
