Metadata-Version: 2.1
Name: amap
Version: 0.1.26
Summary: Automated mouse atlas propagation
Home-page: UNKNOWN
Author: Adam Tyson, Charly Rousseau, Christian Niedworok
Author-email: adam.tyson@ucl.ac.uk
License: UNKNOWN
Project-URL: Source Code, https://github.com/SainsburyWellcomeCentre/amap-python
Project-URL: Bug Tracker, https://github.com/SainsburyWellcomeCentre/amap-python/issues
Platform: UNKNOWN
Classifier: Development Status :: 3 - Alpha
Classifier: Operating System :: POSIX :: Linux
Classifier: Operating System :: Microsoft :: Windows :: Windows 10
Classifier: Programming Language :: Python
Classifier: Programming Language :: Python :: 3.6
Classifier: Programming Language :: Python :: 3.7
Classifier: Programming Language :: Python :: 3.8
Classifier: Intended Audience :: Developers
Classifier: Intended Audience :: Science/Research
Requires-Python: >=3.6, <3.8
Requires-Dist: nibabel
Requires-Dist: numpy
Requires-Dist: configparser
Requires-Dist: pandas (<=0.25.3,>=0.25.1)
Requires-Dist: scikit-image
Requires-Dist: tqdm
Requires-Dist: natsort
Requires-Dist: multiprocessing-logging
Requires-Dist: configobj
Requires-Dist: slurmio
Requires-Dist: brainio (>=0.0.19)
Requires-Dist: fancylog
Requires-Dist: micrometa
Requires-Dist: imlib (>=0.0.25)
Requires-Dist: dask (>=2.15.0)
Requires-Dist: napari[pyqt5] (>=0.3.0)
Requires-Dist: scikit-image (==0.16.2)
Requires-Dist: neuro (>=0.0.13)
Provides-Extra: dev
Requires-Dist: sphinx ; extra == 'dev'
Requires-Dist: recommonmark ; extra == 'dev'
Requires-Dist: sphinx-rtd-theme ; extra == 'dev'
Requires-Dist: pydoc-markdown ; extra == 'dev'
Requires-Dist: black ; extra == 'dev'
Requires-Dist: pytest-cov ; extra == 'dev'
Requires-Dist: pytest ; extra == 'dev'
Requires-Dist: gitpython ; extra == 'dev'
Requires-Dist: coverage ; extra == 'dev'
